honeybadgermpc/__init__.py
honeybadgermpc/__version__.py
honeybadgermpc-0.0.0.dev0.dist-info/METADATA
honeybadgermpc-0.0.0.dev0.dist-info/RECORD
honeybadgermpc-0.0.0.dev0.dist-info/WHEEL
honeybadgermpc-0.0.0.dev0.dist-info/top_level.txt
